mariax/__init__.py
mariax/cli.py
mariax/client.py
mariax/ddl.py
mariax/django_integration/__init__.py
mariax/django_integration/fields.py
mariax/django_integration/managers.py
mariax/query.py
mariax/vector.py
mariax-1.1.0.dist-info/METADATA
mariax-1.1.0.dist-info/WHEEL
mariax-1.1.0.dist-info/RECORD
