Metadata-Version: 2.4
Name: mariax
Version: 1.1.0
Summary: Django ORM & Python library for MariaDB Vector support
Author: Apurv Chaudhary
Author-email: apurv.sirohi@gmail.com
Requires-Python: >=3.12,<4.0
Classifier: Programming Language :: Python :: 3
Classifier: Programming Language :: Python :: 3.12
Classifier: Programming Language :: Python :: 3.13
Classifier: Programming Language :: Python :: 3.14
Provides-Extra: django
Requires-Dist: django (>=4.2) ; extra == "django"
Requires-Dist: mysql-connector-python
Requires-Dist: mysqlclient (>=2.2.1)
